optiframe/__init__.py
optiframe/framework/__init__.py
optiframe/framework/default_tasks.py
optiframe/framework/errors.py
optiframe/framework/metrics.py
optiframe/framework/optimizer.py
optiframe/framework/tasks.py
optiframe/py.typed
optiframe/workflow_engine/__init__.py
optiframe/workflow_engine/errors.py
optiframe/workflow_engine/step.py
optiframe/workflow_engine/task.py
optiframe/workflow_engine/workflow.py
optiframe-0.5.0.dist-info/METADATA
optiframe-0.5.0.dist-info/entry_points.txt
optiframe-0.5.0.dist-info/LICENSE
optiframe-0.5.0.dist-info/WHEEL
optiframe-0.5.0.dist-info/RECORD
