Metadata-Version: 2.1
Name: optiframe
Version: 0.5.0
Summary: A modular framework for mixed integer programming.
Home-page: https://github.com/TimJentzsch/optiframe
License: MIT
Author: Tim Jentzsch
Author-email: optiframe.projects@timjen.net
Requires-Python: >=3.11.0rc1
Classifier: License :: OSI Approved :: MIT License
Classifier: Programming Language :: Python :: 3
Classifier: Programming Language :: Python :: 3.11
Requires-Dist: pulp (>=2.7.0,<3.0.0)
Project-URL: Repository, https://github.com/TimJentzsch/optiframe
